1/Projeto/Semana 3/Relatório/logica_notas_prioridade.v
// ---------------------------------------------------------------------------
// Modulo: logica_notas_prioridade
// Descricao: Implementa a prioridade da ultima tecla pressionada.
// ---------------------------------------------------------------------------
module logica_notas_prioridade (
    input        clock,
    input        reset,
    input  [6:0] botoes,       
    output reg [2:0] nota_id,  // ID da nota ativa
    output       tem_nota      // Flag se alguma nota deve soar
);

    reg [6:0] botoes_ant;
    assign tem_nota = |botoes;

    always @(posedge clock or posedge reset) begin
        if (reset) begin
            nota_id    <= 3'd0;
            botoes_ant <= 7'd0;
        end else begin
            botoes_ant <= botoes;

            // Override em duas notas: Detecta borda de subida em cada botao
            if      (botoes[0] && !botoes_ant[0]) nota_id <= 3'd1; // Do
            else if (botoes[1] && !botoes_ant[1]) nota_id <= 3'd2; // Re
            else if (botoes[2] && !botoes_ant[2]) nota_id <= 3'd3; // Mi
            else if (botoes[3] && !botoes_ant[3]) nota_id <= 3'd4; // Fa
            else if (botoes[4] && !botoes_ant[4]) nota_id <= 3'd5; // Sol
            else if (botoes[5] && !botoes_ant[5]) nota_id <= 3'd6; // La
            else if (botoes[6] && !botoes_ant[6]) nota_id <= 3'd7; // Si
            
            // Fallback em duas notas: Se a ultima nota ativa foi solta, mas outras estao pressionadas, volta para a de maior indice
            if (tem_nota && !botoes[nota_id-1]) begin
                if      (botoes[6]) nota_id <= 3'd7;
                else if (botoes[5]) nota_id <= 3'd6;
                else if (botoes[4]) nota_id <= 3'd5;
                else if (botoes[3]) nota_id <= 3'd4;
                else if (botoes[2]) nota_id <= 3'd3;
                else if (botoes[1]) nota_id <= 3'd2;
                else if (botoes[0]) nota_id <= 3'd1;
            end
        end
    end

endmodule

1/Projeto/Semana 2/Relatório/tb_logica_notas_prioridade.v
`timescale 1ns/1ns

module tb_logica_notas_prioridade;

    reg clock;
    reg reset;
    reg [6:0] botoes;

    wire [2:0] nota_id;
    wire tem_nota;

    logica_notas_prioridade dut (
        .clock(clock),
        .reset(reset),
        .botoes(botoes),
        .nota_id(nota_id),
        .tem_nota(tem_nota)
    );

    // Clock generation
    always #10 clock = ~clock;

    initial begin
        $display("Iniciando Testbench da Logica de Prioridade de Notas...");
        $dumpfile("tb_logica_notas_prioridade.vcd");
        $dumpvars(0, tb_logica_notas_prioridade);

        // Inicializacao
        clock = 0;
        reset = 1;
        botoes = 7'b0000000;

        #25 reset = 0;

        // Toca Do (botao 0)
        #20 botoes = 7'b0000001; 
        #20 $display("Tem nota (1 exp): %b, Nota ID (1 exp): %d", tem_nota, nota_id);

        // Sem soltar o Do, toca Mi (botao 2) -> Override de prioridade por evento
        #20 botoes = 7'b0000101;
        #20 $display("Tem nota (1 exp): %b, Nota ID (3 exp): %d", tem_nota, nota_id);

        // Sem soltar, toca Re (botao 1) -> Novo override
        #20 botoes = 7'b0000111;
        #20 $display("Tem nota (1 exp): %b, Nota ID (2 exp): %d", tem_nota, nota_id);

        // Solta o Re (botao 1), devem sobrar Do e Mi. O Fallback deve assumir a maior nota ativa (Mi = 3)
        #20 botoes = 7'b0000101;
        #20 $display("Tem nota (1 exp): %b, Nota ID (3 exp): %d", tem_nota, nota_id);

        // Solta tudo
        #20 botoes = 7'b0000000;
        #20 $display("Tem nota (0 exp): %b, Nota ID (qualquer exp): %d", tem_nota, nota_id);

        // Fim do teste
        #50;
        $display("Teste Finalizado.");
        $finish;
    end

endmodule

1/Projeto/Semana 3/Planejamento/Testbenchs + Sims/tb_logica_notas_prioridade.vcd
$date
	Sat Mar 28 13:00:37 2026
$end
$version
	Icarus Verilog
$end
$timescale
	1ns
$end
$scope module tb_logica_notas_prioridade $end
$var wire 1 ! tem_nota $end
$var wire 3 " nota_id [2:0] $end
$var reg 7 # botoes [6:0] $end
$var reg 1 $ clock $end
$var reg 1 % reset $end
$scope module dut $end
$var wire 7 & botoes [6:0] $end
$var wire 1 $ clock $end
$var wire 1 % reset $end
$var wire 1 ! tem_nota $end
$var reg 7 ' botoes_ant [6:0] $end
$var reg 3 ( nota_id [2:0] $end
$upscope $end
$upscope $end
$enddefinitions $end
$comment Show the parameter values. $end
$dumpall
$end
#0
$dumpvars
b0 (
b0 '
b0 &
1%
0$
b0 #
b0 "
0!
$end
#10
1$
#20
0$
#25
0%
#30
1$
#40
0$
#45
1!
b1 #
b1 &
#50
b1 "
b1 (
b1 '
1$
#60
0$
#70
1$
#80
0$
#85
b101 #
b101 &
#90
b11 "
b11 (
b101 '
1$
#100
0$
#110
1$
#120
0$
#125
b111 #
b111 &
#130
b10 "
b10 (
b111 '
1$
#140
0$
#150
1$
#160
0$
#165
b101 #
b101 &
#170
b11 "
b11 (
b101 '
1$
#180
0$
#190
1$
#200
0$
#205
0!
b0 #
b0 &
#210
b0 '
1$
