1/Projeto/Semana 3/Planejamento/unidade_controle.v
// ---------------------------------------------------------------------------
// Modulo: unidade_controle
// Descricao: FSM de controle do Piano (Gerencia estados Musicais e de Modo)
// ---------------------------------------------------------------------------
module unidade_controle (
    input clock,
    input reset,
    
    // Entradas
    input mudou_modo,       // Pulso para trocar modo
    input tem_nota_ativa,   
    input acerto_nota,      
    input fim_musica,      
    
    // Saidas de Estado
    output reg modo_aprendizado,
    output reg zera_endereco,
    output reg conta_endereco,
    output reg [4:0] estado_hex // Para depuracao
);

    // Estados da UC
    parameter INICIAL           = 3'd0;
    parameter LIVRE             = 3'd1;
    parameter INICIA_MUSICA     = 3'd2;
    parameter ESPERA_NOTA       = 3'd3;  // Aguarda acerto
    parameter COMPARA_NOTA      = 3'd4;  // Compara nota tocada com a esperada
    parameter PROXIMO           = 3'd5;  // Avanca endereco da ROM
    parameter ESPERA_SOLTAR     = 3'd6;  // Evita que pule duas notas por toque
    parameter FIM_MUSICA_ST     = 3'd7; 

    reg [2:0] state, next_state;

    always @(posedge clock or posedge reset) begin
        if (reset) begin
            state <= INICIAL;
        end else begin
            state <= next_state; 
        end
    end

    // Logica de proximo estado e saidas
    always @(*) begin
        // Valores padrao
        next_state = state;
        modo_aprendizado = 1'b0;
        zera_endereco = 1'b0;
        conta_endereco = 1'b0;
        estado_hex = 5'd0;

        case (state)
            INICIAL: begin
                zera_endereco = 1'b1;
                estado_hex = 5'h0; // Modo Inicial
                
                next_state = LIVRE; // Vai automatico após resetar RAM
            end

            LIVRE: begin
                modo_aprendizado = 1'b0;
                zera_endereco = 1'b1;    // Mantem RAM resetada pro inicio
                estado_hex = 5'h0; // Modo Livre

                if (mudou_modo) next_state = INICIA_MUSICA;
            end
            
            INICIA_MUSICA: begin
                modo_aprendizado = 1'b1;
                zera_endereco = 1'b1;    // Reseta end da ROM
                estado_hex = 5'h2;
                
                next_state = ESPERA_NOTA;
            end

            ESPERA_NOTA: begin
                modo_aprendizado = 1'b1; 
                estado_hex = 5'h2; // Modo Espera

                if (mudou_modo) next_state = LIVRE;
                else if (tem_nota_ativa) next_state = COMPARA_NOTA;
            end
            
            COMPARA_NOTA: begin
                modo_aprendizado = 1'b1; 
                estado_hex = 5'h2;
                
                if (mudou_modo) next_state = LIVRE;
                else if (acerto_nota) next_state = PROXIMO;
                else if (!tem_nota_ativa) next_state = ESPERA_NOTA; 
                // Se errou continua ouvindo o override 
            end

            PROXIMO: begin
                modo_aprendizado = 1'b1; 
                estado_hex = 5'h4; // Modo proximo
                conta_endereco = 1'b1; // Puxa gatilho do contador

                next_state = ESPERA_SOLTAR;
            end

            ESPERA_SOLTAR: begin
                modo_aprendizado = 1'b1;
                estado_hex = 5'h5; // Estado aguardando parar de tocar a nota
                
                if (mudou_modo) next_state = LIVRE;
                else if (!tem_nota_ativa) begin
                    if (fim_musica) next_state = FIM_MUSICA_ST;
                    else next_state = ESPERA_NOTA;
                end
            end

            FIM_MUSICA_ST: begin
                modo_aprendizado = 1'b0; // Apaga leds pra indicar fim
                estado_hex = 5'h2;
                
                if (mudou_modo) next_state = LIVRE;
            end
            
            default: next_state = INICIAL;
        endcase
    end
endmodule

1/Projeto/Semana 3/Planejamento/Testbenchs + Sims/tb_unidade_controle.v
`timescale 1ns/1ns

module tb_unidade_controle;

    reg clock;
    reg reset;
    reg mudou_modo;
    reg tem_nota_ativa;
    reg acerto_nota;
    reg fim_musica;

    wire modo_aprendizado;
    wire zera_endereco;
    wire conta_endereco;
    wire [4:0] estado_hex;

    unidade_controle dut (
        .clock(clock),
        .reset(reset),
        .mudou_modo(mudou_modo),
        .tem_nota_ativa(tem_nota_ativa),
        .acerto_nota(acerto_nota),
        .fim_musica(fim_musica),
        .modo_aprendizado(modo_aprendizado),
        .zera_endereco(zera_endereco),
        .conta_endereco(conta_endereco),
        .estado_hex(estado_hex)
    );

    always #10 clock = ~clock;

    initial begin
        $display("Iniciando Testbench da Unidade de Controle...");
        $dumpfile("tb_unidade_controle.vcd");
        $dumpvars(0, tb_unidade_controle);

        // Inicializacao
        clock = 0;
        reset = 1;
        mudou_modo = 0;
        tem_nota_ativa = 0;
        acerto_nota = 0;
        fim_musica = 0;

        #25 reset = 0;
        
        // Verifica transicao para LIVRE
        #20;
        $display("Estado atual (Livre esperado): %h", dut.state);

        // Transicao para INICIA_MUSICA -> ESPERA_NOTA
        mudou_modo = 1; #20 mudou_modo = 0;
        #20;
        $display("Estado atual (Espera Nota esperado): %h", dut.state);

        // Simula o usuario errando uma nota
        tem_nota_ativa = 1; 
        acerto_nota = 0;
        #20;
        $display("Estado atual (Compara Nota - Erro esperado): %h", dut.state);
        
        // Simula o usuario acertando a nota
        acerto_nota = 1;
        #20;
        $display("Estado atual (Proximo esperado): %h", dut.state);

        // Volta para Espera Soltar
        #20;
        $display("Estado atual (Espera Soltar esperado): %h", dut.state);

        // O usuario solta a nota
        tem_nota_ativa = 0;
        acerto_nota = 0;
        #20;
        $display("Estado atual (Espera Nota esperado): %h", dut.state);

        // Fim do teste
        #50;
        $display("Teste Finalizado.");
        $finish;
    end

endmodule

1/Projeto/Semana 3/Relatório/tb_unidade_controle.vcd
$date
	Tue Mar 31 00:01:18 2026
$end
$version
	Icarus Verilog
$end
$timescale
	1ns
$end
$scope module tb_unidade_controle $end
$var wire 1 ! zera_endereco $end
$var wire 1 " modo_aprendizado $end
$var wire 5 # estado_hex [4:0] $end
$var wire 1 $ conta_endereco $end
$var reg 1 % acerto_nota $end
$var reg 1 & clock $end
$var reg 1 ' fim_musica $end
$var reg 1 ( mudou_modo $end
$var reg 1 ) reset $end
$var reg 1 * tem_nota_ativa $end
$scope module dut $end
$var wire 1 % acerto_nota $end
$var wire 1 & clock $end
$var wire 1 ' fim_musica $end
$var wire 1 ( mudou_modo $end
$var wire 1 ) reset $end
$var wire 1 * tem_nota_ativa $end
$var parameter 3 + COMPARA_NOTA $end
$var parameter 3 , ESPERA_NOTA $end
$var parameter 3 - ESPERA_SOLTAR $end
$var parameter 3 . FIM_MUSICA_ST $end
$var parameter 3 / INICIAL $end
$var parameter 3 0 INICIA_MUSICA $end
$var parameter 3 1 LIVRE $end
$var parameter 3 2 PROXIMO $end
$var reg 1 $ conta_endereco $end
$var reg 5 3 estado_hex [4:0] $end
$var reg 1 " modo_aprendizado $end
$var reg 3 4 next_state [2:0] $end
$var reg 3 5 state [2:0] $end
$var reg 1 ! zera_endereco $end
$upscope $end
$upscope $end
$enddefinitions $end
$comment Show the parameter values. $end
$dumpall
b101 2
b1 1
b10 0
b0 /
b111 .
b110 -
b11 ,
b100 +
$end
#0
$dumpvars
b0 5
b1 4
b0 3
0*
1)
0(
0'
0&
0%
0$
b0 #
0"
1!
$end
#10
1&
#20
0&
#25
0)
#30
1!
b1 5
1&
#40
0&
#45
b10 4
1!
1(
#50
b11 4
b10 #
b10 3
1"
1!
b10 5
1&
#60
0&
#65
b10 #
b10 3
1!
1"
b11 4
0(
#70
b10 #
b10 3
0!
1"
b11 5
1&
#80
0&
#85
b100 4
b10 #
b10 3
1"
1*
#90
b10 #
b10 3
1"
b100 5
1&
#100
0&
#105
b101 4
b10 #
b10 3
1"
1%
#110
b110 4
1$
b100 #
b100 3
1"
b101 5
1&
#120
0&
#130
b101 #
b101 3
0$
1"
b110 5
1&
#140
0&
#145
b11 4
b101 #
b101 3
1"
0%
0*
#150
b10 #
b10 3
1"
b11 5
1&
